rated_exporter_sdk/__init__.py
rated_exporter_sdk/core/__init__.py
rated_exporter_sdk/core/exceptions.py
rated_exporter_sdk/providers/__init__.py
rated_exporter_sdk/providers/cloudwatch/__init__.py
rated_exporter_sdk/providers/datadog/__init__.py
rated_exporter_sdk/providers/prometheus/__init__.py
rated_exporter_sdk/providers/prometheus/auth.py
rated_exporter_sdk/providers/prometheus/client.py
rated_exporter_sdk/providers/prometheus/errors.py
rated_exporter_sdk/providers/prometheus/types.py
rated_exporter_sdk/providers/prometheus/validation.py
rated_exporter_sdk/providers/prometheus/managed/__init__.py
rated_exporter_sdk/providers/prometheus/managed/gcloud_auth.py
rated_exporter_sdk-1.2.0.dist-info/METADATA
rated_exporter_sdk-1.2.0.dist-info/WHEEL
rated_exporter_sdk-1.2.0.dist-info/licenses/LICENSE.md
rated_exporter_sdk-1.2.0.dist-info/RECORD
