Metadata-Version: 2.3
Name: rated_exporter_sdk
Version: 1.2.0
Summary: Fetch metrics and logs from various cloud providers and monitoring services
Author-email: samtin0x <spm@rated.network>
License: # Rated Labs Ltd. License
Requires-Python: >=3.8
Requires-Dist: google-auth>=2.36.0
Requires-Dist: google<4,>=3.0.0
Requires-Dist: requests>=2.31.0
Requires-Dist: structlog>=24.2.0
Requires-Dist: urllib3<3,>=1.21.1
